{"efVersion":"0.9.3","efModuleName":["Data","Argonaut"],"efExports":[{"ReExportRef":[["Data","Argonaut","Core"],{"TypeRef":["JArray",[]]}]},{"ReExportRef":[["Data","Argonaut","Core"],{"TypeRef":["JAssoc",[]]}]},{"ReExportRef":[["Data","Argonaut","Core"],{"TypeRef":["JBoolean",[]]}]},{"ReExportRef":[["Data","Argonaut","JCursor"],{"TypeRef":["JCursor",["JCursorTop","JField","JIndex"]]}]},{"ReExportRef":[["Data","Argonaut","Core"],{"TypeRef":["JNull",[]]}]},{"ReExportRef":[["Data","Argonaut","Core"],{"TypeRef":["JNumber",[]]}]},{"ReExportRef":[["Data","Argonaut","Core"],{"TypeRef":["JObject",[]]}]},{"ReExportRef":[["Data","Argonaut","Core"],{"TypeRef":["JString",[]]}]},{"ReExportRef":[["Data","Argonaut","Core"],{"TypeRef":["Json",[]]}]},{"ReExportRef":[["Data","Argonaut","JCursor"],{"TypeRef":["JsonPrim",["JsonPrim"]]}]},{"ReExportRef":[["Data","Argonaut","Decode","Class"],{"TypeClassRef":"DecodeJson"}]},{"ReExportRef":[["Data","Argonaut","Encode","Class"],{"TypeClassRef":"EncodeJson"}]},{"ReExportRef":[["Data","Argonaut","Printer"],{"TypeClassRef":"Printer"}]},{"ReExportRef":[["Data","Argonaut","Prisms"],{"ValueRef":{"Ident":"_Array"}}]},{"ReExportRef":[["Data","Argonaut","Prisms"],{"ValueRef":{"Ident":"_Boolean"}}]},{"ReExportRef":[["Data","Argonaut","Traversals"],{"ValueRef":{"Ident":"_JsonArray"}}]},{"ReExportRef":[["Data","Argonaut","Traversals"],{"ValueRef":{"Ident":"_JsonBoolean"}}]},{"ReExportRef":[["Data","Argonaut","Traversals"],{"ValueRef":{"Ident":"_JsonNull"}}]},{"ReExportRef":[["Data","Argonaut","Traversals"],{"ValueRef":{"Ident":"_JsonNumber"}}]},{"ReExportRef":[["Data","Argonaut","Traversals"],{"ValueRef":{"Ident":"_JsonObject"}}]},{"ReExportRef":[["Data","Argonaut","Traversals"],{"ValueRef":{"Ident":"_JsonString"}}]},{"ReExportRef":[["Data","Argonaut","Prisms"],{"ValueRef":{"Ident":"_Null"}}]},{"ReExportRef":[["Data","Argonaut","Prisms"],{"ValueRef":{"Ident":"_Number"}}]},{"ReExportRef":[["Data","Argonaut","Prisms"],{"ValueRef":{"Ident":"_Object"}}]},{"ReExportRef":[["Data","Argonaut","Prisms"],{"ValueRef":{"Ident":"_String"}}]},{"ReExportRef":[["Data","Argonaut","Encode","Combinators"],{"ValueRef":{"Ident":"assoc"}}]},{"ReExportRef":[["Data","Argonaut","JCursor"],{"ValueRef":{"Ident":"cursorGet"}}]},{"ReExportRef":[["Data","Argonaut","JCursor"],{"ValueRef":{"Ident":"cursorSet"}}]},{"ReExportRef":[["Data","Argonaut","Decode","Class"],{"ValueRef":{"Ident":"decodeJson"}}]},{"ReExportRef":[["Data","Argonaut","JCursor"],{"ValueRef":{"Ident":"downField"}}]},{"ReExportRef":[["Data","Argonaut","JCursor"],{"ValueRef":{"Ident":"downIndex"}}]},{"ReExportRef":[["Data","Argonaut","Encode","Class"],{"ValueRef":{"Ident":"encodeJson"}}]},{"ReExportRef":[["Data","Argonaut","JCursor"],{"ValueRef":{"Ident":"exactNull"}}]},{"ReExportRef":[["Data","Argonaut","Encode","Combinators"],{"ValueRef":{"Ident":"extend"}}]},{"ReExportRef":[["Data","Argonaut","JCursor"],{"ValueRef":{"Ident":"fail"}}]},{"ReExportRef":[["Data","Argonaut","Core"],{"ValueRef":{"Ident":"foldJson"}}]},{"ReExportRef":[["Data","Argonaut","Core"],{"ValueRef":{"Ident":"foldJsonArray"}}]},{"ReExportRef":[["Data","Argonaut","Core"],{"ValueRef":{"Ident":"foldJsonBoolean"}}]},{"ReExportRef":[["Data","Argonaut","Core"],{"ValueRef":{"Ident":"foldJsonNull"}}]},{"ReExportRef":[["Data","Argonaut","Core"],{"ValueRef":{"Ident":"foldJsonNumber"}}]},{"ReExportRef":[["Data","Argonaut","Core"],{"ValueRef":{"Ident":"foldJsonObject"}}]},{"ReExportRef":[["Data","Argonaut","Core"],{"ValueRef":{"Ident":"foldJsonString"}}]},{"ReExportRef":[["Data","Argonaut","Core"],{"ValueRef":{"Ident":"fromArray"}}]},{"ReExportRef":[["Data","Argonaut","Core"],{"ValueRef":{"Ident":"fromBoolean"}}]},{"ReExportRef":[["Data","Argonaut","Core"],{"ValueRef":{"Ident":"fromNull"}}]},{"ReExportRef":[["Data","Argonaut","Core"],{"ValueRef":{"Ident":"fromNumber"}}]},{"ReExportRef":[["Data","Argonaut","Core"],{"ValueRef":{"Ident":"fromObject"}}]},{"ReExportRef":[["Data","Argonaut","JCursor"],{"ValueRef":{"Ident":"fromPrims"}}]},{"ReExportRef":[["Data","Argonaut","Core"],{"ValueRef":{"Ident":"fromString"}}]},{"ReExportRef":[["Data","Argonaut","Decode","Class"],{"ValueRef":{"Ident":"gDecodeJson"}}]},{"ReExportRef":[["Data","Argonaut","Decode","Class"],{"ValueRef":{"Ident":"gDecodeJson'"}}]},{"ReExportRef":[["Data","Argonaut","Encode","Class"],{"ValueRef":{"Ident":"gEncodeJson"}}]},{"ReExportRef":[["Data","Argonaut","Encode","Class"],{"ValueRef":{"Ident":"gEncodeJson'"}}]},{"ReExportRef":[["Data","Argonaut","Decode","Combinators"],{"ValueRef":{"Ident":"getField"}}]},{"ReExportRef":[["Data","Argonaut","JCursor"],{"ValueRef":{"Ident":"inferEmpty"}}]},{"ReExportRef":[["Data","Argonaut","JCursor"],{"ValueRef":{"Ident":"insideOut"}}]},{"ReExportRef":[["Data","Argonaut","Core"],{"ValueRef":{"Ident":"isArray"}}]},{"ReExportRef":[["Data","Argonaut","Core"],{"ValueRef":{"Ident":"isBoolean"}}]},{"ReExportRef":[["Data","Argonaut","Core"],{"ValueRef":{"Ident":"isNull"}}]},{"ReExportRef":[["Data","Argonaut","Core"],{"ValueRef":{"Ident":"isNumber"}}]},{"ReExportRef":[["Data","Argonaut","Core"],{"ValueRef":{"Ident":"isObject"}}]},{"ReExportRef":[["Data","Argonaut","Core"],{"ValueRef":{"Ident":"isString"}}]},{"ReExportRef":[["Data","Argonaut","Core"],{"ValueRef":{"Ident":"jsonEmptyArray"}}]},{"ReExportRef":[["Data","Argonaut","Core"],{"ValueRef":{"Ident":"jsonEmptyObject"}}]},{"ReExportRef":[["Data","Argonaut","Core"],{"ValueRef":{"Ident":"jsonFalse"}}]},{"ReExportRef":[["Data","Argonaut","Core"],{"ValueRef":{"Ident":"jsonNull"}}]},{"ReExportRef":[["Data","Argonaut","Parser"],{"ValueRef":{"Ident":"jsonParser"}}]},{"ReExportRef":[["Data","Argonaut","Core"],{"ValueRef":{"Ident":"jsonSingletonArray"}}]},{"ReExportRef":[["Data","Argonaut","Core"],{"ValueRef":{"Ident":"jsonSingletonObject"}}]},{"ReExportRef":[["Data","Argonaut","Core"],{"ValueRef":{"Ident":"jsonTrue"}}]},{"ReExportRef":[["Data","Argonaut","Core"],{"ValueRef":{"Ident":"jsonZero"}}]},{"ReExportRef":[["Data","Argonaut","JCursor"],{"ValueRef":{"Ident":"primBool"}}]},{"ReExportRef":[["Data","Argonaut","JCursor"],{"ValueRef":{"Ident":"primNull"}}]},{"ReExportRef":[["Data","Argonaut","JCursor"],{"ValueRef":{"Ident":"primNum"}}]},{"ReExportRef":[["Data","Argonaut","JCursor"],{"ValueRef":{"Ident":"primStr"}}]},{"ReExportRef":[["Data","Argonaut","JCursor"],{"ValueRef":{"Ident":"primToJson"}}]},{"ReExportRef":[["Data","Argonaut","Printer"],{"ValueRef":{"Ident":"printJson"}}]},{"ReExportRef":[["Data","Argonaut","JCursor"],{"ValueRef":{"Ident":"runJsonPrim"}}]},{"ReExportRef":[["Data","Argonaut","Core"],{"ValueRef":{"Ident":"toArray"}}]},{"ReExportRef":[["Data","Argonaut","Core"],{"ValueRef":{"Ident":"toBoolean"}}]},{"ReExportRef":[["Data","Argonaut","Core"],{"ValueRef":{"Ident":"toNull"}}]},{"ReExportRef":[["Data","Argonaut","Core"],{"ValueRef":{"Ident":"toNumber"}}]},{"ReExportRef":[["Data","Argonaut","Core"],{"ValueRef":{"Ident":"toObject"}}]},{"ReExportRef":[["Data","Argonaut","JCursor"],{"ValueRef":{"Ident":"toPrims"}}]},{"ReExportRef":[["Data","Argonaut","Core"],{"ValueRef":{"Ident":"toString"}}]},{"ReExportRef":[["Data","Argonaut","Decode","Combinators"],{"ValueOpRef":".?"}]},{"ReExportRef":[["Data","Argonaut","Encode","Combinators"],{"ValueOpRef":":="}]},{"ReExportRef":[["Data","Argonaut","Encode","Combinators"],{"ValueOpRef":"~>"}]},{"PositionedDeclarationRef":[{"start":[2,5],"name":"/home/yannick/dev/conchord-ui/bower_components/purescript-argonaut/src/Data/Argonaut.purs","end":[2,30]},[],{"ModuleRef":["Data","Argonaut","Core"]}]},{"PositionedDeclarationRef":[{"start":[3,5],"name":"/home/yannick/dev/conchord-ui/bower_components/purescript-argonaut/src/Data/Argonaut.purs","end":[3,32]},[],{"ModuleRef":["Data","Argonaut","Decode"]}]},{"PositionedDeclarationRef":[{"start":[4,5],"name":"/home/yannick/dev/conchord-ui/bower_components/purescript-argonaut/src/Data/Argonaut.purs","end":[4,32]},[],{"ModuleRef":["Data","Argonaut","Encode"]}]},{"PositionedDeclarationRef":[{"start":[5,5],"name":"/home/yannick/dev/conchord-ui/bower_components/purescript-argonaut/src/Data/Argonaut.purs","end":[5,33]},[],{"ModuleRef":["Data","Argonaut","JCursor"]}]},{"PositionedDeclarationRef":[{"start":[6,5],"name":"/home/yannick/dev/conchord-ui/bower_components/purescript-argonaut/src/Data/Argonaut.purs","end":[6,32]},[],{"ModuleRef":["Data","Argonaut","Parser"]}]},{"PositionedDeclarationRef":[{"start":[7,5],"name":"/home/yannick/dev/conchord-ui/bower_components/purescript-argonaut/src/Data/Argonaut.purs","end":[7,33]},[],{"ModuleRef":["Data","Argonaut","Printer"]}]},{"PositionedDeclarationRef":[{"start":[8,5],"name":"/home/yannick/dev/conchord-ui/bower_components/purescript-argonaut/src/Data/Argonaut.purs","end":[8,32]},[],{"ModuleRef":["Data","Argonaut","Prisms"]}]},{"PositionedDeclarationRef":[{"start":[9,5],"name":"/home/yannick/dev/conchord-ui/bower_components/purescript-argonaut/src/Data/Argonaut.purs","end":[9,36]},[],{"ModuleRef":["Data","Argonaut","Traversals"]}]}],"efImports":[{"eiModule":["Prim"],"eiImportType":{"Implicit":[]},"eiImportedAs":null},{"eiModule":["Data","Argonaut","Core"],"eiImportType":{"Explicit":[{"PositionedDeclarationRef":[{"start":[12,28],"name":"/home/yannick/dev/conchord-ui/bower_components/purescript-argonaut/src/Data/Argonaut.purs","end":[12,34]},[],{"TypeRef":["JArray",[]]}]},{"PositionedDeclarationRef":[{"start":[12,36],"name":"/home/yannick/dev/conchord-ui/bower_components/purescript-argonaut/src/Data/Argonaut.purs","end":[12,42]},[],{"TypeRef":["JAssoc",[]]}]},{"PositionedDeclarationRef":[{"start":[12,44],"name":"/home/yannick/dev/conchord-ui/bower_components/purescript-argonaut/src/Data/Argonaut.purs","end":[12,52]},[],{"TypeRef":["JBoolean",[]]}]},{"PositionedDeclarationRef":[{"start":[12,54],"name":"/home/yannick/dev/conchord-ui/bower_components/purescript-argonaut/src/Data/Argonaut.purs","end":[12,59]},[],{"TypeRef":["JNull",[]]}]},{"PositionedDeclarationRef":[{"start":[12,61],"name":"/home/yannick/dev/conchord-ui/bower_components/purescript-argonaut/src/Data/Argonaut.purs","end":[12,68]},[],{"TypeRef":["JNumber",[]]}]},{"PositionedDeclarationRef":[{"start":[12,70],"name":"/home/yannick/dev/conchord-ui/bower_components/purescript-argonaut/src/Data/Argonaut.purs","end":[12,77]},[],{"TypeRef":["JObject",[]]}]},{"PositionedDeclarationRef":[{"start":[12,79],"name":"/home/yannick/dev/conchord-ui/bower_components/purescript-argonaut/src/Data/Argonaut.purs","end":[12,86]},[],{"TypeRef":["JString",[]]}]},{"PositionedDeclarationRef":[{"start":[12,88],"name":"/home/yannick/dev/conchord-ui/bower_components/purescript-argonaut/src/Data/Argonaut.purs","end":[12,92]},[],{"TypeRef":["Json",[]]}]},{"PositionedDeclarationRef":[{"start":[12,94],"name":"/home/yannick/dev/conchord-ui/bower_components/purescript-argonaut/src/Data/Argonaut.purs","end":[12,102]},[],{"ValueRef":{"Ident":"foldJson"}}]},{"PositionedDeclarationRef":[{"start":[12,104],"name":"/home/yannick/dev/conchord-ui/bower_components/purescript-argonaut/src/Data/Argonaut.purs","end":[12,117]},[],{"ValueRef":{"Ident":"foldJsonArray"}}]},{"PositionedDeclarationRef":[{"start":[12,119],"name":"/home/yannick/dev/conchord-ui/bower_components/purescript-argonaut/src/Data/Argonaut.purs","end":[12,134]},[],{"ValueRef":{"Ident":"foldJsonBoolean"}}]},{"PositionedDeclarationRef":[{"start":[12,136],"name":"/home/yannick/dev/conchord-ui/bower_components/purescript-argonaut/src/Data/Argonaut.purs","end":[12,148]},[],{"ValueRef":{"Ident":"foldJsonNull"}}]},{"PositionedDeclarationRef":[{"start":[12,150],"name":"/home/yannick/dev/conchord-ui/bower_components/purescript-argonaut/src/Data/Argonaut.purs","end":[12,164]},[],{"ValueRef":{"Ident":"foldJsonNumber"}}]},{"PositionedDeclarationRef":[{"start":[12,166],"name":"/home/yannick/dev/conchord-ui/bower_components/purescript-argonaut/src/Data/Argonaut.purs","end":[12,180]},[],{"ValueRef":{"Ident":"foldJsonObject"}}]},{"PositionedDeclarationRef":[{"start":[12,182],"name":"/home/yannick/dev/conchord-ui/bower_components/purescript-argonaut/src/Data/Argonaut.purs","end":[12,196]},[],{"ValueRef":{"Ident":"foldJsonString"}}]},{"PositionedDeclarationRef":[{"start":[12,198],"name":"/home/yannick/dev/conchord-ui/bower_components/purescript-argonaut/src/Data/Argonaut.purs","end":[12,207]},[],{"ValueRef":{"Ident":"fromArray"}}]},{"PositionedDeclarationRef":[{"start":[12,209],"name":"/home/yannick/dev/conchord-ui/bower_components/purescript-argonaut/src/Data/Argonaut.purs","end":[12,220]},[],{"ValueRef":{"Ident":"fromBoolean"}}]},{"PositionedDeclarationRef":[{"start":[12,222],"name":"/home/yannick/dev/conchord-ui/bower_components/purescript-argonaut/src/Data/Argonaut.purs","end":[12,230]},[],{"ValueRef":{"Ident":"fromNull"}}]},{"PositionedDeclarationRef":[{"start":[12,232],"name":"/home/yannick/dev/conchord-ui/bower_components/purescript-argonaut/src/Data/Argonaut.purs","end":[12,242]},[],{"ValueRef":{"Ident":"fromNumber"}}]},{"PositionedDeclarationRef":[{"start":[12,244],"name":"/home/yannick/dev/conchord-ui/bower_components/purescript-argonaut/src/Data/Argonaut.purs","end":[12,254]},[],{"ValueRef":{"Ident":"fromObject"}}]},{"PositionedDeclarationRef":[{"start":[12,256],"name":"/home/yannick/dev/conchord-ui/bower_components/purescript-argonaut/src/Data/Argonaut.purs","end":[12,266]},[],{"ValueRef":{"Ident":"fromString"}}]},{"PositionedDeclarationRef":[{"start":[12,268],"name":"/home/yannick/dev/conchord-ui/bower_components/purescript-argonaut/src/Data/Argonaut.purs","end":[12,275]},[],{"ValueRef":{"Ident":"isArray"}}]},{"PositionedDeclarationRef":[{"start":[12,277],"name":"/home/yannick/dev/conchord-ui/bower_components/purescript-argonaut/src/Data/Argonaut.purs","end":[12,286]},[],{"ValueRef":{"Ident":"isBoolean"}}]},{"PositionedDeclarationRef":[{"start":[12,288],"name":"/home/yannick/dev/conchord-ui/bower_components/purescript-argonaut/src/Data/Argonaut.purs","end":[12,294]},[],{"ValueRef":{"Ident":"isNull"}}]},{"PositionedDeclarationRef":[{"start":[12,296],"name":"/home/yannick/dev/conchord-ui/bower_components/purescript-argonaut/src/Data/Argonaut.purs","end":[12,304]},[],{"ValueRef":{"Ident":"isNumber"}}]},{"PositionedDeclarationRef":[{"start":[12,306],"name":"/home/yannick/dev/conchord-ui/bower_components/purescript-argonaut/src/Data/Argonaut.purs","end":[12,314]},[],{"ValueRef":{"Ident":"isObject"}}]},{"PositionedDeclarationRef":[{"start":[12,316],"name":"/home/yannick/dev/conchord-ui/bower_components/purescript-argonaut/src/Data/Argonaut.purs","end":[12,324]},[],{"ValueRef":{"Ident":"isString"}}]},{"PositionedDeclarationRef":[{"start":[12,326],"name":"/home/yannick/dev/conchord-ui/bower_components/purescript-argonaut/src/Data/Argonaut.purs","end":[12,340]},[],{"ValueRef":{"Ident":"jsonEmptyArray"}}]},{"PositionedDeclarationRef":[{"start":[12,342],"name":"/home/yannick/dev/conchord-ui/bower_components/purescript-argonaut/src/Data/Argonaut.purs","end":[12,357]},[],{"ValueRef":{"Ident":"jsonEmptyObject"}}]},{"PositionedDeclarationRef":[{"start":[12,359],"name":"/home/yannick/dev/conchord-ui/bower_components/purescript-argonaut/src/Data/Argonaut.purs","end":[12,368]},[],{"ValueRef":{"Ident":"jsonFalse"}}]},{"PositionedDeclarationRef":[{"start":[12,370],"name":"/home/yannick/dev/conchord-ui/bower_components/purescript-argonaut/src/Data/Argonaut.purs","end":[12,378]},[],{"ValueRef":{"Ident":"jsonNull"}}]},{"PositionedDeclarationRef":[{"start":[12,380],"name":"/home/yannick/dev/conchord-ui/bower_components/purescript-argonaut/src/Data/Argonaut.purs","end":[12,398]},[],{"ValueRef":{"Ident":"jsonSingletonArray"}}]},{"PositionedDeclarationRef":[{"start":[12,400],"name":"/home/yannick/dev/conchord-ui/bower_components/purescript-argonaut/src/Data/Argonaut.purs","end":[12,419]},[],{"ValueRef":{"Ident":"jsonSingletonObject"}}]},{"PositionedDeclarationRef":[{"start":[12,421],"name":"/home/yannick/dev/conchord-ui/bower_components/purescript-argonaut/src/Data/Argonaut.purs","end":[12,429]},[],{"ValueRef":{"Ident":"jsonTrue"}}]},{"PositionedDeclarationRef":[{"start":[12,431],"name":"/home/yannick/dev/conchord-ui/bower_components/purescript-argonaut/src/Data/Argonaut.purs","end":[12,439]},[],{"ValueRef":{"Ident":"jsonZero"}}]},{"PositionedDeclarationRef":[{"start":[12,441],"name":"/home/yannick/dev/conchord-ui/bower_components/purescript-argonaut/src/Data/Argonaut.purs","end":[12,448]},[],{"ValueRef":{"Ident":"toArray"}}]},{"PositionedDeclarationRef":[{"start":[12,450],"name":"/home/yannick/dev/conchord-ui/bower_components/purescript-argonaut/src/Data/Argonaut.purs","end":[12,459]},[],{"ValueRef":{"Ident":"toBoolean"}}]},{"PositionedDeclarationRef":[{"start":[12,461],"name":"/home/yannick/dev/conchord-ui/bower_components/purescript-argonaut/src/Data/Argonaut.purs","end":[12,467]},[],{"ValueRef":{"Ident":"toNull"}}]},{"PositionedDeclarationRef":[{"start":[12,469],"name":"/home/yannick/dev/conchord-ui/bower_components/purescript-argonaut/src/Data/Argonaut.purs","end":[12,477]},[],{"ValueRef":{"Ident":"toNumber"}}]},{"PositionedDeclarationRef":[{"start":[12,479],"name":"/home/yannick/dev/conchord-ui/bower_components/purescript-argonaut/src/Data/Argonaut.purs","end":[12,487]},[],{"ValueRef":{"Ident":"toObject"}}]},{"PositionedDeclarationRef":[{"start":[12,489],"name":"/home/yannick/dev/conchord-ui/bower_components/purescript-argonaut/src/Data/Argonaut.purs","end":[12,497]},[],{"ValueRef":{"Ident":"toString"}}]}]},"eiImportedAs":null},{"eiModule":["Data","Argonaut","Decode"],"eiImportType":{"Explicit":[{"PositionedDeclarationRef":[{"start":[13,30],"name":"/home/yannick/dev/conchord-ui/bower_components/purescript-argonaut/src/Data/Argonaut.purs","end":[13,46]},[],{"TypeClassRef":"DecodeJson"}]},{"PositionedDeclarationRef":[{"start":[13,48],"name":"/home/yannick/dev/conchord-ui/bower_components/purescript-argonaut/src/Data/Argonaut.purs","end":[13,58]},[],{"ValueRef":{"Ident":"decodeJson"}}]},{"PositionedDeclarationRef":[{"start":[13,60],"name":"/home/yannick/dev/conchord-ui/bower_components/purescript-argonaut/src/Data/Argonaut.purs","end":[13,71]},[],{"ValueRef":{"Ident":"gDecodeJson"}}]},{"PositionedDeclarationRef":[{"start":[13,73],"name":"/home/yannick/dev/conchord-ui/bower_components/purescript-argonaut/src/Data/Argonaut.purs","end":[13,85]},[],{"ValueRef":{"Ident":"gDecodeJson'"}}]},{"PositionedDeclarationRef":[{"start":[13,87],"name":"/home/yannick/dev/conchord-ui/bower_components/purescript-argonaut/src/Data/Argonaut.purs","end":[13,95]},[],{"ValueRef":{"Ident":"getField"}}]},{"PositionedDeclarationRef":[{"start":[13,97],"name":"/home/yannick/dev/conchord-ui/bower_components/purescript-argonaut/src/Data/Argonaut.purs","end":[13,101]},[],{"ValueOpRef":".?"}]}]},"eiImportedAs":null},{"eiModule":["Data","Argonaut","Encode"],"eiImportType":{"Explicit":[{"PositionedDeclarationRef":[{"start":[14,30],"name":"/home/yannick/dev/conchord-ui/bower_components/purescript-argonaut/src/Data/Argonaut.purs","end":[14,46]},[],{"TypeClassRef":"EncodeJson"}]},{"PositionedDeclarationRef":[{"start":[14,48],"name":"/home/yannick/dev/conchord-ui/bower_components/purescript-argonaut/src/Data/Argonaut.purs","end":[14,53]},[],{"ValueRef":{"Ident":"assoc"}}]},{"PositionedDeclarationRef":[{"start":[14,55],"name":"/home/yannick/dev/conchord-ui/bower_components/purescript-argonaut/src/Data/Argonaut.purs","end":[14,65]},[],{"ValueRef":{"Ident":"encodeJson"}}]},{"PositionedDeclarationRef":[{"start":[14,67],"name":"/home/yannick/dev/conchord-ui/bower_components/purescript-argonaut/src/Data/Argonaut.purs","end":[14,73]},[],{"ValueRef":{"Ident":"extend"}}]},{"PositionedDeclarationRef":[{"start":[14,75],"name":"/home/yannick/dev/conchord-ui/bower_components/purescript-argonaut/src/Data/Argonaut.purs","end":[14,86]},[],{"ValueRef":{"Ident":"gEncodeJson"}}]},{"PositionedDeclarationRef":[{"start":[14,88],"name":"/home/yannick/dev/conchord-ui/bower_components/purescript-argonaut/src/Data/Argonaut.purs","end":[14,100]},[],{"ValueRef":{"Ident":"gEncodeJson'"}}]},{"PositionedDeclarationRef":[{"start":[14,102],"name":"/home/yannick/dev/conchord-ui/bower_components/purescript-argonaut/src/Data/Argonaut.purs","end":[14,106]},[],{"ValueOpRef":":="}]},{"PositionedDeclarationRef":[{"start":[14,108],"name":"/home/yannick/dev/conchord-ui/bower_components/purescript-argonaut/src/Data/Argonaut.purs","end":[14,112]},[],{"ValueOpRef":"~>"}]}]},"eiImportedAs":null},{"eiModule":["Data","Argonaut","JCursor"],"eiImportType":{"Explicit":[{"PositionedDeclarationRef":[{"start":[15,31],"name":"/home/yannick/dev/conchord-ui/bower_components/purescript-argonaut/src/Data/Argonaut.purs","end":[15,42]},[],{"TypeRef":["JCursor",null]}]},{"PositionedDeclarationRef":[{"start":[15,44],"name":"/home/yannick/dev/conchord-ui/bower_components/purescript-argonaut/src/Data/Argonaut.purs","end":[15,56]},[],{"TypeRef":["JsonPrim",null]}]},{"PositionedDeclarationRef":[{"start":[15,58],"name":"/home/yannick/dev/conchord-ui/bower_components/purescript-argonaut/src/Data/Argonaut.purs","end":[15,67]},[],{"ValueRef":{"Ident":"cursorGet"}}]},{"PositionedDeclarationRef":[{"start":[15,69],"name":"/home/yannick/dev/conchord-ui/bower_components/purescript-argonaut/src/Data/Argonaut.purs","end":[15,78]},[],{"ValueRef":{"Ident":"cursorSet"}}]},{"PositionedDeclarationRef":[{"start":[15,80],"name":"/home/yannick/dev/conchord-ui/bower_components/purescript-argonaut/src/Data/Argonaut.purs","end":[15,89]},[],{"ValueRef":{"Ident":"downField"}}]},{"PositionedDeclarationRef":[{"start":[15,91],"name":"/home/yannick/dev/conchord-ui/bower_components/purescript-argonaut/src/Data/Argonaut.purs","end":[15,100]},[],{"ValueRef":{"Ident":"downIndex"}}]},{"PositionedDeclarationRef":[{"start":[15,102],"name":"/home/yannick/dev/conchord-ui/bower_components/purescript-argonaut/src/Data/Argonaut.purs","end":[15,111]},[],{"ValueRef":{"Ident":"exactNull"}}]},{"PositionedDeclarationRef":[{"start":[15,113],"name":"/home/yannick/dev/conchord-ui/bower_components/purescript-argonaut/src/Data/Argonaut.purs","end":[15,117]},[],{"ValueRef":{"Ident":"fail"}}]},{"PositionedDeclarationRef":[{"start":[15,119],"name":"/home/yannick/dev/conchord-ui/bower_components/purescript-argonaut/src/Data/Argonaut.purs","end":[15,128]},[],{"ValueRef":{"Ident":"fromPrims"}}]},{"PositionedDeclarationRef":[{"start":[15,130],"name":"/home/yannick/dev/conchord-ui/bower_components/purescript-argonaut/src/Data/Argonaut.purs","end":[15,140]},[],{"ValueRef":{"Ident":"inferEmpty"}}]},{"PositionedDeclarationRef":[{"start":[15,142],"name":"/home/yannick/dev/conchord-ui/bower_components/purescript-argonaut/src/Data/Argonaut.purs","end":[15,151]},[],{"ValueRef":{"Ident":"insideOut"}}]},{"PositionedDeclarationRef":[{"start":[15,153],"name":"/home/yannick/dev/conchord-ui/bower_components/purescript-argonaut/src/Data/Argonaut.purs","end":[15,161]},[],{"ValueRef":{"Ident":"primBool"}}]},{"PositionedDeclarationRef":[{"start":[15,163],"name":"/home/yannick/dev/conchord-ui/bower_components/purescript-argonaut/src/Data/Argonaut.purs","end":[15,171]},[],{"ValueRef":{"Ident":"primNull"}}]},{"PositionedDeclarationRef":[{"start":[15,173],"name":"/home/yannick/dev/conchord-ui/bower_components/purescript-argonaut/src/Data/Argonaut.purs","end":[15,180]},[],{"ValueRef":{"Ident":"primNum"}}]},{"PositionedDeclarationRef":[{"start":[15,182],"name":"/home/yannick/dev/conchord-ui/bower_components/purescript-argonaut/src/Data/Argonaut.purs","end":[15,189]},[],{"ValueRef":{"Ident":"primStr"}}]},{"PositionedDeclarationRef":[{"start":[15,191],"name":"/home/yannick/dev/conchord-ui/bower_components/purescript-argonaut/src/Data/Argonaut.purs","end":[15,201]},[],{"ValueRef":{"Ident":"primToJson"}}]},{"PositionedDeclarationRef":[{"start":[15,203],"name":"/home/yannick/dev/conchord-ui/bower_components/purescript-argonaut/src/Data/Argonaut.purs","end":[15,214]},[],{"ValueRef":{"Ident":"runJsonPrim"}}]},{"PositionedDeclarationRef":[{"start":[15,216],"name":"/home/yannick/dev/conchord-ui/bower_components/purescript-argonaut/src/Data/Argonaut.purs","end":[15,223]},[],{"ValueRef":{"Ident":"toPrims"}}]}]},"eiImportedAs":null},{"eiModule":["Data","Argonaut","Parser"],"eiImportType":{"Explicit":[{"PositionedDeclarationRef":[{"start":[16,30],"name":"/home/yannick/dev/conchord-ui/bower_components/purescript-argonaut/src/Data/Argonaut.purs","end":[16,40]},[],{"ValueRef":{"Ident":"jsonParser"}}]}]},"eiImportedAs":null},{"eiModule":["Data","Argonaut","Printer"],"eiImportType":{"Explicit":[{"PositionedDeclarationRef":[{"start":[17,31],"name":"/home/yannick/dev/conchord-ui/bower_components/purescript-argonaut/src/Data/Argonaut.purs","end":[17,44]},[],{"TypeClassRef":"Printer"}]},{"PositionedDeclarationRef":[{"start":[17,46],"name":"/home/yannick/dev/conchord-ui/bower_components/purescript-argonaut/src/Data/Argonaut.purs","end":[17,55]},[],{"ValueRef":{"Ident":"printJson"}}]}]},"eiImportedAs":null},{"eiModule":["Data","Argonaut","Prisms"],"eiImportType":{"Explicit":[{"PositionedDeclarationRef":[{"start":[18,30],"name":"/home/yannick/dev/conchord-ui/bower_components/purescript-argonaut/src/Data/Argonaut.purs","end":[18,36]},[],{"ValueRef":{"Ident":"_Array"}}]},{"PositionedDeclarationRef":[{"start":[18,38],"name":"/home/yannick/dev/conchord-ui/bower_components/purescript-argonaut/src/Data/Argonaut.purs","end":[18,46]},[],{"ValueRef":{"Ident":"_Boolean"}}]},{"PositionedDeclarationRef":[{"start":[18,48],"name":"/home/yannick/dev/conchord-ui/bower_components/purescript-argonaut/src/Data/Argonaut.purs","end":[18,53]},[],{"ValueRef":{"Ident":"_Null"}}]},{"PositionedDeclarationRef":[{"start":[18,55],"name":"/home/yannick/dev/conchord-ui/bower_components/purescript-argonaut/src/Data/Argonaut.purs","end":[18,62]},[],{"ValueRef":{"Ident":"_Number"}}]},{"PositionedDeclarationRef":[{"start":[18,64],"name":"/home/yannick/dev/conchord-ui/bower_components/purescript-argonaut/src/Data/Argonaut.purs","end":[18,71]},[],{"ValueRef":{"Ident":"_Object"}}]},{"PositionedDeclarationRef":[{"start":[18,73],"name":"/home/yannick/dev/conchord-ui/bower_components/purescript-argonaut/src/Data/Argonaut.purs","end":[18,80]},[],{"ValueRef":{"Ident":"_String"}}]}]},"eiImportedAs":null},{"eiModule":["Data","Argonaut","Traversals"],"eiImportType":{"Explicit":[{"PositionedDeclarationRef":[{"start":[19,34],"name":"/home/yannick/dev/conchord-ui/bower_components/purescript-argonaut/src/Data/Argonaut.purs","end":[19,44]},[],{"ValueRef":{"Ident":"_JsonArray"}}]},{"PositionedDeclarationRef":[{"start":[19,46],"name":"/home/yannick/dev/conchord-ui/bower_components/purescript-argonaut/src/Data/Argonaut.purs","end":[19,58]},[],{"ValueRef":{"Ident":"_JsonBoolean"}}]},{"PositionedDeclarationRef":[{"start":[19,60],"name":"/home/yannick/dev/conchord-ui/bower_components/purescript-argonaut/src/Data/Argonaut.purs","end":[19,69]},[],{"ValueRef":{"Ident":"_JsonNull"}}]},{"PositionedDeclarationRef":[{"start":[19,71],"name":"/home/yannick/dev/conchord-ui/bower_components/purescript-argonaut/src/Data/Argonaut.purs","end":[19,82]},[],{"ValueRef":{"Ident":"_JsonNumber"}}]},{"PositionedDeclarationRef":[{"start":[19,84],"name":"/home/yannick/dev/conchord-ui/bower_components/purescript-argonaut/src/Data/Argonaut.purs","end":[19,95]},[],{"ValueRef":{"Ident":"_JsonObject"}}]},{"PositionedDeclarationRef":[{"start":[19,97],"name":"/home/yannick/dev/conchord-ui/bower_components/purescript-argonaut/src/Data/Argonaut.purs","end":[19,108]},[],{"ValueRef":{"Ident":"_JsonString"}}]}]},"eiImportedAs":null}],"efFixities":[],"efTypeFixities":[],"efDeclarations":[]}